{"50000": {"min-out-degree": 0, "max-out-degree": 359, "avg-out-degree": 0.7005842872956045, "std-out-degree": 3.208911777009479, "min-in-degree": 0, "max-in-degree": 35, "avg-in-degree": 0.7005842872956045, "std-in-degree": 0.7071294263445903, "min-betweeness": 0.0, "max-betweeness": 9.808592323026793e-06, "avg-betweeness": 4.1230473972005187e-10, "std-betweeness": 5.374470812147732e-08, "min-closeness": 0.0, "max-closeness": 0.0004943391996412958, "avg-closeness": 1.3240083355814186e-05, "std-closeness": 1.855106331679769e-05, "min-neighboor-degree": 0.0, "max-neighboor-degree": 329.0, "avg-neighboor-degree": 0.29666249150811197, "std-neighboor-degree": 3.106438504480826, "count-scc": 71369, "min-scc": 1, "max-scc": 1, "avg-scc": 1.0, "std-scc": 0.0, "count-wcc": 21883, "min-wcc": 2, "max-wcc": 17580, "avg-wcc": 3.2613901201846183, "std-wcc": 118.84300704296354}, "100000": {"min-out-degree": 0, "max-out-degree": 719, "avg-out-degree": 0.7776291642041743, "std-out-degree": 4.762061540210603, "min-in-degree": 0, "max-in-degree": 65, "avg-in-degree": 0.7776291642041743, "std-in-degree": 0.8898610293504701, "min-betweeness": 0.0, "max-betweeness": 0.0, "avg-betweeness": 0.0, "std-betweeness": 0.0, "min-closeness": 0.0, "max-closeness": 0.0007579067125364915, "avg-closeness": 1.316085755020999e-05, "std-closeness": 2.8275990948966343e-05, "min-neighboor-degree": 0.0, "max-neighboor-degree": 510.0, "avg-neighboor-degree": 0.555773247683011, "std-neighboor-degree": 5.020985945387167, "count-scc": 128596, "min-scc": 1, "max-scc": 1, "avg-scc": 1.0, "std-scc": 0.0, "count-wcc": 33617, "min-wcc": 2, "max-wcc": 49710, "avg-wcc": 3.825326471725615, "std-wcc": 271.10803305393074}, "150000": {"min-out-degree": 0, "max-out-degree": 1070, "avg-out-degree": 0.8402608169575836, "std-out-degree": 5.989647868397637, "min-in-degree": 0, "max-in-degree": 84, "avg-in-degree": 0.8402608169575836, "std-in-degree": 1.0700992274696437, "min-betweeness": 0.0, "max-betweeness": 8.402749379069649e-06, "avg-betweeness": 5.334600799337652e-11, "std-betweeness": 2.0063550246022055e-08, "min-closeness": 0.0, "max-closeness": 0.001308288549066303, "avg-closeness": 2.321662222588466e-05, "std-closeness": 7.321239060503579e-05, "min-neighboor-degree": 0.0, "max-neighboor-degree": 973.0, "avg-neighboor-degree": 0.8241547905994245, "std-neighboor-degree": 8.336108029889967, "count-scc": 178516, "min-scc": 1, "max-scc": 1, "avg-scc": 1.0, "std-scc": 0.0, "count-wcc": 41736, "min-wcc": 2, "max-wcc": 81789, "avg-wcc": 4.277266628330458, "std-wcc": 400.3351413556162}, "200000": {"min-out-degree": 0, "max-out-degree": 1335, "avg-out-degree": 0.8900796176217962, "std-out-degree": 7.089885216015181, "min-in-degree": 0, "max-in-degree": 135, "avg-in-degree": 0.8900796176217962, "std-in-degree": 1.2761788360126896, "min-betweeness": 0.0, "max-betweeness": 8.010823512339771e-06, "avg-betweeness": 1.5845046063775727e-10, "std-betweeness": 2.6119603396610082e-08, "min-closeness": 0.0, "max-closeness": 0.001967369711385357, "avg-closeness": 4.8037655071302366e-05, "std-closeness": 0.00014573321707044462, "min-neighboor-degree": 0.0, "max-neighboor-degree": 1105.0, "avg-neighboor-degree": 1.0972657038416187, "std-neighboor-degree": 10.170881194692523, "count-scc": 224699, "min-scc": 1, "max-scc": 1, "avg-scc": 1.0, "std-scc": 0.0, "count-wcc": 49052, "min-wcc": 2, "max-wcc": 111384, "avg-wcc": 4.580832585827285, "std-wcc": 502.90039174182675}, "250000": {"min-out-degree": 0, "max-out-degree": 1762, "avg-out-degree": 0.9343628766416756, "std-out-degree": 8.077649764245432, "min-in-degree": 0, "max-in-degree": 146, "avg-in-degree": 0.9343628766416756, "std-in-degree": 1.4214643049904345, "min-betweeness": 0.0, "max-betweeness": 0.0, "avg-betweeness": 0.0, "std-betweeness": 0.0, "min-closeness": 0.0, "max-closeness": 0.002724760930977031, "avg-closeness": 7.582471270523611e-05, "std-closeness": 0.00020897868578374667, "min-neighboor-degree": 0.0, "max-neighboor-degree": 1762.0, "avg-neighboor-degree": 1.3478481160238107, "std-neighboor-degree": 12.92842374548271, "count-scc": 267562, "min-scc": 1, "max-scc": 1, "avg-scc": 1.0, "std-scc": 0.0, "count-wcc": 54826, "min-wcc": 2, "max-wcc": 140314, "avg-wcc": 4.880202823477912, "std-wcc": 599.2351171806425}, "300000": {"min-out-degree": 0, "max-out-degree": 2108, "avg-out-degree": 0.9729866473799091, "std-out-degree": 9.103363046116932, "min-in-degree": 0, "max-in-degree": 179, "avg-in-degree": 0.9729866473799091, "std-in-degree": 1.5715236618538828, "min-betweeness": 0.0, "max-betweeness": 0.0, "avg-betweeness": 0.0, "std-betweeness": 0.0, "min-closeness": 0.0, "max-closeness": 0.0038495269765940203, "avg-closeness": 0.00010793289149530993, "std-closeness": 0.00028957208586474244, "min-neighboor-degree": 0.0, "max-neighboor-degree": 1572.0, "avg-neighboor-degree": 1.5764687941769258, "std-neighboor-degree": 13.81778881260248, "count-scc": 308329, "min-scc": 1, "max-scc": 1, "avg-scc": 1.0, "std-scc": 0.0, "count-wcc": 60017, "min-wcc": 2, "max-wcc": 168836, "avg-wcc": 5.137361081027042, "std-wcc": 689.1579668169986}, "350000": {"min-out-degree": 0, "max-out-degree": 2448, "avg-out-degree": 1.0097775315843986, "std-out-degree": 10.00322238255908, "min-in-degree": 0, "max-in-degree": 216, "avg-in-degree": 1.0097775315843986, "std-in-degree": 1.7247905113938, "min-betweeness": 0.0, "max-betweeness": 2.7696994875594864e-05, "avg-betweeness": 2.4138877690944455e-10, "std-betweeness": 6.667516078103282e-08, "min-closeness": 0.0, "max-closeness": 0.005125343047344064, "avg-closeness": 0.0001570225180456716, "std-closeness": 0.0003908972850759486, "min-neighboor-degree": 0.0, "max-neighboor-degree": 1806.0, "avg-neighboor-degree": 1.7890415975391483, "std-neighboor-degree": 15.138779676720956, "count-scc": 346611, "min-scc": 1, "max-scc": 1, "avg-scc": 1.0, "std-scc": 0.0, "count-wcc": 64380, "min-wcc": 2, "max-wcc": 196604, "avg-wcc": 5.383830382106244, "std-wcc": 774.8340379292584}, "400000": {"min-out-degree": 0, "max-out-degree": 2752, "avg-out-degree": 1.0457598360248577, "std-out-degree": 10.876405230122492, "min-in-degree": 0, "max-in-degree": 238, "avg-in-degree": 1.0457598360248577, "std-in-degree": 1.8551242511092463, "min-betweeness": 0.0, "max-betweeness": 1.307210047721441e-06, "avg-betweeness": 4.784597178043271e-12, "std-betweeness": 2.196555637576155e-09, "min-closeness": 0.0, "max-closeness": 0.004947582866041789, "avg-closeness": 0.00021115085322465934, "std-closeness": 0.0004885041647335961, "min-neighboor-degree": 0.0, "max-neighboor-degree": 2739.0, "avg-neighboor-degree": 2.0180377243383685, "std-neighboor-degree": 18.845204569365062, "count-scc": 382497, "min-scc": 1, "max-scc": 1, "avg-scc": 1.0, "std-scc": 0.0, "count-wcc": 68112, "min-wcc": 2, "max-wcc": 223089, "avg-wcc": 5.615706483439042, "std-wcc": 854.7888982025491}, "450000": {"min-out-degree": 0, "max-out-degree": 3214, "avg-out-degree": 1.0768641715324974, "std-out-degree": 11.788283125040378, "min-in-degree": 0, "max-in-degree": 273, "avg-in-degree": 1.0768641715324974, "std-in-degree": 1.9954571280836992, "min-betweeness": 0.0, "max-betweeness": 1.3161767697042446e-05, "avg-betweeness": 1.0651551953365888e-10, "std-betweeness": 2.769739817476178e-08, "min-closeness": 0.0, "max-closeness": 0.006523357561830446, "avg-closeness": 0.00024257214617392348, "std-closeness": 0.0005438478945960442, "min-neighboor-degree": 0.0, "max-neighboor-degree": 3214.0, "avg-neighboor-degree": 2.2150782967882074, "std-neighboor-degree": 20.267487632515135, "count-scc": 417880, "min-scc": 1, "max-scc": 1, "avg-scc": 1.0, "std-scc": 0.0, "count-wcc": 71485, "min-wcc": 2, "max-wcc": 249608, "avg-wcc": 5.845701895502553, "std-wcc": 933.5641213018562}, "500000": {"min-out-degree": 0, "max-out-degree": 3518, "avg-out-degree": 1.1092131242096857, "std-out-degree": 12.681988116529027, "min-in-degree": 0, "max-in-degree": 315, "avg-in-degree": 1.1092131242096857, "std-in-degree": 2.1152411310992325, "min-betweeness": 0.0, "max-betweeness": 2.883973316563112e-06, "avg-betweeness": 9.842895546468733e-12, "std-betweeness": 4.530522408282858e-09, "min-closeness": 0.0, "max-closeness": 0.007619171181624067, "avg-closeness": 0.00028375659006894767, "std-closeness": 0.0006130608242095988, "min-neighboor-degree": 0.0, "max-neighboor-degree": 2760.0, "avg-neighboor-degree": 2.447256474866511, "std-neighboor-degree": 22.620377565795387, "count-scc": 450770, "min-scc": 1, "max-scc": 1, "avg-scc": 1.0, "std-scc": 0.0, "count-wcc": 74338, "min-wcc": 2, "max-wcc": 275222, "avg-wcc": 6.063789717237483, "std-wcc": 1009.4185011702755}}